river-0.20.1.dist-info/WHEEL
river-0.20.1.dist-info/LICENSE
river-0.20.1.dist-info/RECORD
river-0.20.1.dist-info/METADATA
river/conftest.py
river/api.py
river/__version__.py
river/py.typed
river/dummy.py
river/test_estimators.py
river/__init__.py
river/linear_model/alma.py
river/linear_model/lin_reg.py
river/linear_model/bayesian_lin_reg.py
river/linear_model/pa.py
river/linear_model/softmax.py
river/linear_model/base.py
river/linear_model/__init__.py
river/linear_model/perceptron.py
river/linear_model/test_glm.py
river/linear_model/log_reg.py
river/multiclass/ovr.py
river/multiclass/occ.py
river/multiclass/ovo.py
river/multiclass/test_ovr.py
river/multiclass/__init__.py
river/naive_bayes/gaussian.py
river/naive_bayes/multinomial.py
river/naive_bayes/bernoulli.py
river/naive_bayes/complement.py
river/naive_bayes/base.py
river/naive_bayes/__init__.py
river/naive_bayes/test_naive_bayes.py
river/misc/__init__.py
river/misc/sdft.py
river/misc/skyline.py
river/multioutput/chain.py
river/multioutput/encoder.py
river/multioutput/__init__.py
river/optim/initializers.py
river/optim/nadam.py
river/optim/adam.py
river/optim/schedulers.py
river/optim/ams_grad.py
river/optim/nesterov.py
river/optim/test_.py
river/optim/ada_delta.py
river/optim/losses.py
river/optim/ada_grad.py
river/optim/base.py
river/optim/ada_max.py
river/optim/ftrl.py
river/optim/average.py
river/optim/__init__.py
river/optim/momentum.py
river/optim/ada_bound.py
river/optim/sgd.py
river/optim/rms_prop.py
river/optim/newton.py
river/tree/test_base.py
river/tree/hoeffding_tree_regressor.py
river/tree/hoeffding_adaptive_tree_regressor.py
river/tree/test_trees.py
river/tree/viz.py
river/tree/stochastic_gradient_tree.py
river/tree/hoeffding_tree.py
river/tree/utils.py
river/tree/setup.py
river/tree/extremely_fast_decision_tree.py
river/tree/isoup_tree_regressor.py
river/tree/losses.py
river/tree/base.py
river/tree/hoeffding_tree_classifier.py
river/tree/hoeffding_adaptive_tree_classifier.py
river/tree/__init__.py
river/tree/test_splitter.py
