Metadata-Version: 2.1
Name: river
Version: 0.20.1
Summary: Online machine learning in Python
Home-page: https://riverml.xyz/
Author: Max Halford
Author-email: maxhalford25@gmail.com
Requires-Python: >=3.9,<3.13
Classifier: Programming Language :: Python :: 3
Classifier: Programming Language :: Python :: 3.9
Classifier: Programming Language :: Python :: 3.10
Classifier: Programming Language :: Python :: 3.11
Classifier: Programming Language :: Python :: 3.12
Requires-Dist: pandas (>=2.1,<3.0)
Requires-Dist: scipy (>=1.8.1,<2.0.0)
Project-URL: Repository, https://github.com/online-ml/river/
